thmcli/__init__.py
thmcli/cli.py
thmcli/commands/__init__.py
thmcli/commands/auth.py
thmcli/commands/room.py
thmcli/util/__init__.py
thmcli/util/api.py
thmcli-0.1.0.dist-info/LICENSE
thmcli-0.1.0.dist-info/METADATA
thmcli-0.1.0.dist-info/WHEEL
thmcli-0.1.0.dist-info/entry_points.txt
thmcli-0.1.0.dist-info/top_level.txt
thmcli-0.1.0.dist-info/RECORD
